{
    "source": {
        "title": "50 Journals used in FT Research Rank",
        "link": "https://www.ft.com/content/3405a512-5cbb-11e1-8f1f-00144feabdc0/"
    },
    "data": [
        {
            "title": "Accounting Review",
            "subjectArea": "Accounting",
            "printIssn": "0001-4826",
            "onlineIssn": ""
        },
        {
            "title": "Accounting, Organizations and Society",
            "subjectArea": "Accounting",
            "printIssn": "0361-3682",
            "onlineIssn": ""
        },
        {
            "title": "Contemporary Accounting Research",
            "subjectArea": "Accounting",
            "printIssn": "0823-9150",
            "onlineIssn": ""
        },
        {
            "title": "Journal of Accounting and Economics",
            "subjectArea": "Accounting",
            "printIssn": "0165-4101",
            "onlineIssn": ""
        },
        {
            "title": "Journal of Accounting Research",
            "subjectArea": "Accounting",
            "printIssn": "0021-8456",
            "onlineIssn": ""
        },
        {
            "title": "Review of Accounting Studies",
            "subjectArea": "Accounting",
            "printIssn": "1380-6653",
            "onlineIssn": ""
        },
        {
            "title": "American Economic Review",
            "subjectArea": "Economics",
            "printIssn": "0002-8282",
            "onlineIssn": ""
        },
        {
            "title": "Econometrica",
            "subjectArea": "Economics",
            "printIssn": "0012-9682",
            "onlineIssn": ""
        },
        {
            "title": "Journal of Political Economy",
            "subjectArea": "Economics",
            "printIssn": "0022-3808",
            "onlineIssn": ""
        },
        {
            "title": "Quarterly Journal of Economics",
            "subjectArea": "Economics",
            "printIssn": "0033-5533",
            "onlineIssn": ""
        },
        {
            "title": "Research Policy",
            "subjectArea": "Economics, Management",
            "printIssn": "0048-7333",
            "onlineIssn": ""
        },
        {
            "title": "Review of Economic Studies",
            "subjectArea": "Economics",
            "printIssn": "0034-6527",
            "onlineIssn": ""
        },
        {
            "title": "Entrepreneurship Theory and Practice",
            "subjectArea": "Entrepreneurship",
            "printIssn": "1042-2587",
            "onlineIssn": ""
        },
        {
            "title": "Journal of Business Venturing",
            "subjectArea": "Entrepreneurship",
            "printIssn": "0883-9026",
            "onlineIssn": ""
        },
        {
            "title": "Strategic Entrepreneurship Journal",
            "subjectArea": "Entrepreneurship",
            "printIssn": "1932-4391",
            "onlineIssn": ""
        },
        {
            "title": "Journal of Business Ethics",
            "subjectArea": "Ethics",
            "printIssn": "0167-4544",
            "onlineIssn": ""
        },
        {
            "title": "Journal of Finance",
            "subjectArea": "Finance",
            "printIssn": "0022-1082",
            "onlineIssn": ""
        },
        {
            "title": "Journal of Financial and Quantitative Analysis",
            "subjectArea": "Finance",
            "printIssn": "0022-1090",
            "onlineIssn": ""
        },
        {
            "title": "Journal of Financial Economics",
            "subjectArea": "Finance",
            "printIssn": "0304-405X",
            "onlineIssn": ""
        },
        {
            "title": "Review of Finance",
            "subjectArea": "Finance",
            "printIssn": "1572-3097",
            "onlineIssn": ""
        },
        {
            "title": "Review of Financial Studies",
            "subjectArea": "Finance",
            "printIssn": "0893-9454",
            "onlineIssn": ""
        },
        {
            "title": "Human Relations",
            "subjectArea": "Human Resources",
            "printIssn": "0018-7267",
            "onlineIssn": "1741-282X"
        },
        {
            "title": "Human Resource Management",
            "subjectArea": "Human Resources",
            "printIssn": "0090-4848",
            "onlineIssn": ""
        },
        {
            "title": "Information Systems Research",
            "subjectArea": "Information Systems",
            "printIssn": "1047-7047",
            "onlineIssn": ""
        },
        {
            "title": "Journal of Management Information Systems",
            "subjectArea": "Information Systems",
            "printIssn": "0742-1222",
            "onlineIssn": ""
        },
        {
            "title": "MIS Quarterly",
            "subjectArea": "Information Systems",
            "printIssn": "0276-7783",
            "onlineIssn": ""
        },
        {
            "title": "Journal of International Business Studies",
            "subjectArea": "International Business",
            "printIssn": "0047-2506",
            "onlineIssn": ""
        },
        {
            "title": "Academy of Management Journal",
            "subjectArea": "Management",
            "printIssn": "0001-4273",
            "onlineIssn": ""
        },
        {
            "title": "Academy of Management Review",
            "subjectArea": "Management",
            "printIssn": "0363-7425",
            "onlineIssn": ""
        },
        {
            "title": "Administrative Science Quarterly",
            "subjectArea": "Management",
            "printIssn": "0001-8392",
            "onlineIssn": ""
        },
        {
            "title": "Harvard Business Review",
            "subjectArea": "Management",
            "printIssn": "0017-8012",
            "onlineIssn": ""
        },
        {
            "title": "Journal of Management",
            "subjectArea": "Management",
            "printIssn": "0149-2063",
            "onlineIssn": ""
        },
        {
            "title": "Journal of Management Studies",
            "subjectArea": "Management",
            "printIssn": "0022-2380",
            "onlineIssn": ""
        },
        {
            "title": "Management Science",
            "subjectArea": "Management",
            "printIssn": "0025-1909",
            "onlineIssn": ""
        },
        {
            "title": "MIT Sloan Management Review",
            "subjectArea": "Management",
            "printIssn": "1532-8937",
            "onlineIssn": ""
        },
        {
            "title": "Strategic Management Journal",
            "subjectArea": "Management",
            "printIssn": "0143-2095",
            "onlineIssn": ""
        },
        {
            "title": "Journal of Consumer Psychology",
            "subjectArea": "Marketing",
            "printIssn": "1057-7408",
            "onlineIssn": ""
        },
        {
            "title": "Journal of Consumer Research",
            "subjectArea": "Marketing",
            "printIssn": "0093-5301",
            "onlineIssn": ""
        },
        {
            "title": "Journal of Marketing",
            "subjectArea": "Marketing",
            "printIssn": "0022-2429",
            "onlineIssn": ""
        },
        {
            "title": "Journal of Marketing Research",
            "subjectArea": "Marketing",
            "printIssn": "0022-2437",
            "onlineIssn": ""
        },
        {
            "title": "Journal of the Academy of Marketing Science",
            "subjectArea": "Marketing",
            "printIssn": "0092-0703",
            "onlineIssn": ""
        },
        {
            "title": "Marketing Science",
            "subjectArea": "Marketing",
            "printIssn": "0732-2399",
            "onlineIssn": ""
        },
        {
            "title": "Journal of Operations Management",
            "subjectArea": "Operations",
            "printIssn": "0272-6963",
            "onlineIssn": ""
        },
        {
            "title": "Manufacturing & Service Operations Management",
            "subjectArea": "Operations",
            "printIssn": "1523-4614",
            "onlineIssn": ""
        },
        {
            "title": "Operations Research",
            "subjectArea": "Operations",
            "printIssn": "0030-364X",
            "onlineIssn": ""
        },
        {
            "title": "Production and Operations Management",
            "subjectArea": "Operations",
            "printIssn": "1059-1478",
            "onlineIssn": ""
        },
        {
            "title": "Journal of Applied Psychology",
            "subjectArea": "Organizational Behaviour",
            "printIssn": "0021-9010",
            "onlineIssn": ""
        },
        {
            "title": "Organization Science",
            "subjectArea": "Organizational Behaviour",
            "printIssn": "1047-7039",
            "onlineIssn": ""
        },
        {
            "title": "Organization Studies",
            "subjectArea": "Organizational Behaviour",
            "printIssn": "0170-8406",
            "onlineIssn": ""
        },
        {
            "title": "Organizational Behavior and Human Decision Processes",
            "subjectArea": "Organizational Behaviour",
            "printIssn": "0749-5978",
            "onlineIssn": ""
        }
    ]
}